wallpaper_factory/__init__.py
wallpaper_factory/available_palletes.py
wallpaper_factory/main.py
wallpaper_factory/palletes.json
wallpaper_factory-0.1.4.dist-info/LICENSE
wallpaper_factory-0.1.4.dist-info/METADATA
wallpaper_factory-0.1.4.dist-info/WHEEL
wallpaper_factory-0.1.4.dist-info/entry_points.txt
wallpaper_factory-0.1.4.dist-info/top_level.txt
wallpaper_factory-0.1.4.dist-info/RECORD
