Metadata-Version: 2.1
Name: wallpaper_factory
Version: 0.1.4
Summary: This package changes images to follow some specific color schemes.
License-File: LICENSE
Requires-Dist: opencv-python
Requires-Dist: pillow
